cisco_netbox_onboarding/Adjacency.py
cisco_netbox_onboarding/Connections.py
cisco_netbox_onboarding/CustomExceptions.py
cisco_netbox_onboarding/Device.py
cisco_netbox_onboarding/IPAM.py
cisco_netbox_onboarding/Interface.py
cisco_netbox_onboarding/Inventory.py
cisco_netbox_onboarding/Netbox_Connector.py
cisco_netbox_onboarding/New_Onboard.py
cisco_netbox_onboarding/Tasks.py
cisco_netbox_onboarding/VirtualChassis.py
cisco_netbox_onboarding/__init__.py
cisco_netbox_onboarding/inventory_helper.py
cisco_netbox_onboarding-0.0.11.dist-info/licenses/LICENSE
cisco_netbox_onboarding-0.0.11.dist-info/METADATA
cisco_netbox_onboarding-0.0.11.dist-info/WHEEL
cisco_netbox_onboarding-0.0.11.dist-info/top_level.txt
cisco_netbox_onboarding-0.0.11.dist-info/RECORD
