Metadata-Version: 2.4
Name: cisco_netbox_onboarding
Version: 0.0.11
Summary: A Package to onboard Cisco devices to Netbox
Author-email: Tarani Debnath <tkdebnath@aol.com>
Maintainer-email: Tarani Debnath <tkdebnath@aol.com>
License:                     GNU GENERAL PUBLIC LICENSE
Project-URL: Homepage, https://github.com/tkdebnath/cisco_netbox_onboarding
Project-URL: Repository, https://github.com/tkdebnath/cisco_netbox_onboarding
Project-URL: Bug Tracker, https://github.com/tkdebnath/cisco_netbox_onboarding/issues
Keywords: netbox onboarding,logical interfaces,physical interface,ip assignment,virtual chassis,cable connection,netbox api
Classifier: Development Status :: 3 - Alpha
Classifier: Programming Language :: Python :: 3
Classifier: Programming Language :: Python :: 3.10
Classifier: Programming Language :: Python :: 3.11
Classifier: Programming Language :: Python :: 3.12
Classifier: Programming Language :: Python :: 3.13
Requires-Python: >=3.10
License-File: LICENSE
Requires-Dist: requests>=2.32.3
Requires-Dist: pynetbox>=7.4.1
Requires-Dist: genie>=25.2
Requires-Dist: pyats>=25.2
Requires-Dist: netmiko>=4.5.0
Requires-Dist: dotenv>=0.9.9
Dynamic: license-file
